tescmd/__init__.py
tescmd/__main__.py
tescmd/py.typed
tescmd/_internal/__init__.py
tescmd/_internal/async_utils.py
tescmd/_internal/permissions.py
tescmd/_internal/vin.py
tescmd/api/__init__.py
tescmd/api/charging.py
tescmd/api/client.py
tescmd/api/command.py
tescmd/api/energy.py
tescmd/api/errors.py
tescmd/api/partner.py
tescmd/api/sharing.py
tescmd/api/signed_command.py
tescmd/api/user.py
tescmd/api/vehicle.py
tescmd/auth/__init__.py
tescmd/auth/oauth.py
tescmd/auth/server.py
tescmd/auth/token_store.py
tescmd/ble/__init__.py
tescmd/cache/__init__.py
tescmd/cache/keys.py
tescmd/cache/response_cache.py
tescmd/cli/__init__.py
tescmd/cli/_client.py
tescmd/cli/_options.py
tescmd/cli/auth.py
tescmd/cli/billing.py
tescmd/cli/cache.py
tescmd/cli/charge.py
tescmd/cli/climate.py
tescmd/cli/energy.py
tescmd/cli/key.py
tescmd/cli/main.py
tescmd/cli/media.py
tescmd/cli/nav.py
tescmd/cli/partner.py
tescmd/cli/raw.py
tescmd/cli/security.py
tescmd/cli/setup.py
tescmd/cli/sharing.py
tescmd/cli/software.py
tescmd/cli/status.py
tescmd/cli/trunk.py
tescmd/cli/user.py
tescmd/cli/vehicle.py
tescmd/config/__init__.py
tescmd/crypto/__init__.py
tescmd/crypto/ecdh.py
tescmd/crypto/keys.py
tescmd/crypto/schnorr.py
tescmd/deploy/__init__.py
tescmd/deploy/github_pages.py
tescmd/deploy/tailscale_serve.py
tescmd/models/__init__.py
tescmd/models/auth.py
tescmd/models/command.py
tescmd/models/config.py
tescmd/models/energy.py
tescmd/models/sharing.py
tescmd/models/user.py
tescmd/models/vehicle.py
tescmd/output/__init__.py
tescmd/output/formatter.py
tescmd/output/json_output.py
tescmd/output/rich_output.py
tescmd/protocol/__init__.py
tescmd/protocol/commands.py
tescmd/protocol/encoder.py
tescmd/protocol/metadata.py
tescmd/protocol/payloads.py
tescmd/protocol/session.py
tescmd/protocol/signer.py
tescmd/protocol/protobuf/__init__.py
tescmd/protocol/protobuf/messages.py
tescmd/telemetry/__init__.py
tescmd/telemetry/dashboard.py
tescmd/telemetry/decoder.py
tescmd/telemetry/fields.py
tescmd-0.2.0.dist-info/METADATA
tescmd-0.2.0.dist-info/WHEEL
tescmd-0.2.0.dist-info/entry_points.txt
tescmd-0.2.0.dist-info/licenses/LICENSE
tescmd-0.2.0.dist-info/RECORD
