Metadata-Version: 2.4
Name: tescmd
Version: 0.2.0
Summary: A Python CLI for querying and controlling Tesla vehicles via the Fleet API
Project-URL: Homepage, https://github.com/oceanswave/tescmd
Project-URL: Repository, https://github.com/oceanswave/tescmd
Project-URL: Issues, https://github.com/oceanswave/tescmd/issues
Project-URL: Documentation, https://github.com/oceanswave/tescmd#readme
Author: oceanswave
License-Expression: MIT
License-File: LICENSE
Keywords: cli,ev,fleet-api,tesla,vehicle
Classifier: Development Status :: 4 - Beta
Classifier: Environment :: Console
Classifier: Intended Audience :: Developers
Classifier: License :: OSI Approved :: MIT License
Classifier: Operating System :: OS Independent
Classifier: Programming Language :: Python :: 3
Classifier: Programming Language :: Python :: 3.11
Classifier: Programming Language :: Python :: 3.12
Classifier: Programming Language :: Python :: 3.13
Classifier: Topic :: Software Development :: Libraries
Classifier: Typing :: Typed
Requires-Python: >=3.11
Requires-Dist: click>=8.1
Requires-Dist: cryptography>=42.0
Requires-Dist: httpx>=0.27
Requires-Dist: keyring>=25.0
Requires-Dist: protobuf>=5.29
Requires-Dist: pydantic-settings>=2.0
Requires-Dist: pydantic>=2.0
Requires-Dist: python-dotenv>=1.0
Requires-Dist: rich>=13.0
Provides-Extra: ble
Requires-Dist: bleak>=0.22; extra == 'ble'
Provides-Extra: dev
Requires-Dist: build>=1.0; extra == 'dev'
Requires-Dist: grpcio-tools>=1.68; extra == 'dev'
Requires-Dist: mypy-protobuf>=3.6; extra == 'dev'
Requires-Dist: mypy>=1.13; extra == 'dev'
Requires-Dist: pytest-asyncio>=0.24; extra == 'dev'
Requires-Dist: pytest-cov>=5.0; extra == 'dev'
Requires-Dist: pytest-httpx>=0.34; extra == 'dev'
Requires-Dist: pytest-xdist>=3.0; extra == 'dev'
Requires-Dist: pytest>=8.0; extra == 'dev'
Requires-Dist: ruff>=0.8; extra == 'dev'
Provides-Extra: telemetry
Requires-Dist: websockets>=14.0; extra == 'telemetry'
